sq/__init__.py
sq/version.py
shadyquant-0.1.0.dist-info/LICENSE
shadyquant-0.1.0.dist-info/METADATA
shadyquant-0.1.0.dist-info/WHEEL
shadyquant-0.1.0.dist-info/top_level.txt
shadyquant-0.1.0.dist-info/RECORD
