Metadata-Version: 2.1
Name: shadyquant
Version: 0.1.0
Summary: Shaded quantile plot
Home-page: https://github.com/whitead/shadyquant
Author: Andrew White <andrew.white@rochester.edu>, Mehrad Ansari <Mehrad.ansari@rochester.edu>
Author-email: andrew.white@rochester.edu
License: GPL v2
Platform: UNKNOWN
Classifier: Development Status :: 2 - Pre-Alpha
Classifier: License :: OSI Approved :: GNU General Public License v2 (GPLv2)
Classifier: Programming Language :: Python
Classifier: Programming Language :: Python :: 3
Classifier: Programming Language :: Python :: 3.8
Classifier: Programming Language :: Python :: 3.5
Classifier: Programming Language :: Python :: 3.6
Classifier: Programming Language :: Python :: 3.7
License-File: LICENSE
Requires-Dist: numpy
Requires-Dist: matplotlib
